st_track_viewer/__init__.py
st_track_viewer/extract_installation.py
st_track_viewer/extract_result.py
st_track_viewer/helper.py
st_track_viewer/frontend/build/asset-manifest.json
st_track_viewer/frontend/build/index.html
st_track_viewer/frontend/build/static/css/main.1375c1ec.chunk.css
st_track_viewer/frontend/build/static/css/main.1375c1ec.chunk.css.map
st_track_viewer/frontend/build/static/js/2.d4f6fb3b.chunk.js
st_track_viewer/frontend/build/static/js/2.d4f6fb3b.chunk.js.LICENSE.txt
st_track_viewer/frontend/build/static/js/2.d4f6fb3b.chunk.js.map
st_track_viewer/frontend/build/static/js/main.7d2f0eb6.chunk.js
st_track_viewer/frontend/build/static/js/main.7d2f0eb6.chunk.js.map
st_track_viewer/frontend/build/static/js/runtime-main.39defc4e.js
st_track_viewer/frontend/build/static/js/runtime-main.39defc4e.js.map
st_track_viewer-0.2.4.dist-info/LICENSE
st_track_viewer-0.2.4.dist-info/METADATA
st_track_viewer-0.2.4.dist-info/WHEEL
st_track_viewer-0.2.4.dist-info/top_level.txt
st_track_viewer-0.2.4.dist-info/RECORD
