Metadata-Version: 2.1
Name: st-track-viewer
Version: 0.2.4
Summary: A Streamlit component for visualizing track data on images
Home-page: 
Author: Elliot Glas
Author-email: elliot.glas@viscando.com
Requires-Python: >=3.6
License-File: LICENSE
Requires-Dist: streamlit (>=0.63)
